README.md
setup.cfg
setup.py
laueagle/__init__.py
laueagle/pjson.py
laueagle/pyaml.py
laueagle/sample_module.py
laueagle.egg-info/PKG-INFO
laueagle.egg-info/SOURCES.txt
laueagle.egg-info/dependency_links.txt
laueagle.egg-info/entry_points.txt
laueagle.egg-info/requires.txt
laueagle.egg-info/top_level.txt
laueagle/jsonlint/__init__.py
laueagle/jsonlint/demjson.py
laueagle/jsonlint/jsonlint.py
laueagle/yamllint/__init__.py
laueagle/yamllint/config.py
laueagle/yamllint/linter.py
laueagle/yamllint/parser.py
laueagle/yamllint/rules/__init__.py
laueagle/yamllint/rules/braces.py
laueagle/yamllint/rules/brackets.py
laueagle/yamllint/rules/colons.py
laueagle/yamllint/rules/commas.py
laueagle/yamllint/rules/comments.py
laueagle/yamllint/rules/comments_indentation.py
laueagle/yamllint/rules/common.py
laueagle/yamllint/rules/document_end.py
laueagle/yamllint/rules/document_start.py
laueagle/yamllint/rules/empty_lines.py
laueagle/yamllint/rules/empty_values.py
laueagle/yamllint/rules/hyphens.py
laueagle/yamllint/rules/indentation.py
laueagle/yamllint/rules/key_duplicates.py
laueagle/yamllint/rules/key_ordering.py
laueagle/yamllint/rules/line_length.py
laueagle/yamllint/rules/new_line_at_end_of_file.py
laueagle/yamllint/rules/new_lines.py
laueagle/yamllint/rules/octal_values.py
laueagle/yamllint/rules/trailing_spaces.py
laueagle/yamllint/rules/truthy.py