Metadata-Version: 1.1
Name: laueagle
Version: 0.0.3
Summary: UNKNOWN
Home-page: https://liqiang.io/opensource/python/laueagle
Author: Liqiang Lau
Author-email: liqianglau@outlook.com
License: MIT
Keywords: cli
Platform: UNKNOWN
Classifier: Development Status :: 1 - Planning
Classifier: Intended Audience :: Science/Research
Classifier: Topic :: Software Development
Classifier: License :: Other/Proprietary License
Classifier: Programming Language :: Python :: 3.6
Classifier: Programming Language :: Python :: 3.5
Classifier: Programming Language :: Python :: 2.7
